pyfrag_plotter/__init__.py
pyfrag_plotter/errors.py
pyfrag_plotter/interpolate.py
pyfrag_plotter/processing_funcs.py
pyfrag_plotter/pyfrag_object.py
pyfrag_plotter/config/__init__.py
pyfrag_plotter/config/config.ini
pyfrag_plotter/config/config_handler.py
pyfrag_plotter/config/validate.py
pyfrag_plotter/input/__init__.py
pyfrag_plotter/input/pyfrag_files.py
pyfrag_plotter/input/read_inputfile.py
pyfrag_plotter/input/read_resultsfile.py
pyfrag_plotter/plot/__init__.py
pyfrag_plotter/plot/plot_details.py
pyfrag_plotter/plot/plotter.py
pyfrag_plotter-1.0.4.dist-info/LICENSE.txt
pyfrag_plotter-1.0.4.dist-info/METADATA
pyfrag_plotter-1.0.4.dist-info/WHEEL
pyfrag_plotter-1.0.4.dist-info/top_level.txt
pyfrag_plotter-1.0.4.dist-info/RECORD
