Metadata-Version: 2.1
Name: pyfrag_plotter
Version: 1.0.4
Summary: Package for plotting pyfrag calculations using the AMS driver and plams
Author-email: Siebe Lekanne Deprez <s.j.lekanne.deprez@vu.nl>
Maintainer-email: Siebe Lekanne Deprez <s.j.lekanne.deprez@vu.nl>
License: MIT
Project-URL: repository, https://github.com/SiebeLeDe/pyfrag_plot
Project-URL: documentation, https://siebelede.github.io/pyfrag_plot/
Classifier: Programming Language :: Python :: 3.8
Classifier: Programming Language :: Python :: 3.9
Classifier: Programming Language :: Python :: 3.10
Classifier: Programming Language :: Python :: 3.11
Classifier: Programming Language :: Python :: 3.12
Classifier: License :: OSI Approved :: MIT License
Classifier: Operating System :: OS Independent
Requires-Python: >=3.8
License-File: LICENSE.txt
Requires-Dist: numpy >=1.20.0
Requires-Dist: pandas >=1.2.4
Requires-Dist: scipy >=1.6.3
Requires-Dist: attrs >=21.2.0
Requires-Dist: matplotlib >=3.3.4
Requires-Dist: sphinx >=3.5.4
Requires-Dist: pydata-sphinx-theme >=0.6.3
Requires-Dist: myst-parser >=0.15.1
